superagent/__init__.py
superagent/client.py
superagent/core/__init__.py
superagent/core/api_error.py
superagent/core/datetime_utils.py
superagent/core/jsonable_encoder.py
superagent/core/remove_none_from_headers.py
superagent/errors/__init__.py
superagent/errors/unprocessable_entity_error.py
superagent/py.typed
superagent/resources/__init__.py
superagent/resources/agent/__init__.py
superagent/resources/agent/client.py
superagent/resources/api_token/__init__.py
superagent/resources/api_token/client.py
superagent/resources/auth/__init__.py
superagent/resources/auth/client.py
superagent/resources/documents/__init__.py
superagent/resources/documents/client.py
superagent/resources/prompts/__init__.py
superagent/resources/prompts/client.py
superagent/resources/tools/__init__.py
superagent/resources/tools/client.py
superagent/resources/traces/__init__.py
superagent/resources/traces/client.py
superagent/resources/user/__init__.py
superagent/resources/user/client.py
superagent/types/__init__.py
superagent/types/http_validation_error.py
superagent/types/validation_error.py
superagent/types/validation_error_loc_item.py
fern_superagent-0.0.5.dist-info/METADATA
fern_superagent-0.0.5.dist-info/WHEEL
fern_superagent-0.0.5.dist-info/RECORD
